<?xml version = '1.0' encoding = 'UTF-8'?>
<Diagram class="oracle.dbtools.crest.swingui.relational.DPVRelationalSubView" name="From_LM_disoders" id="53532C32-5774-DDA1-01B0-4FBEE9CF71C6">
<createdBy>User</createdBy>
<modifiedBy>User</modifiedBy>
<createdTime>2023-03-06 19:53:44 UTC</createdTime>
<autoRoute>false</autoRoute>
<boxInbox>true</boxInbox>
<showLegend>false</showLegend>
<showLabels>false</showLabels>
<showRelAttributes>false</showRelAttributes>
<gridEnabled>false</gridEnabled>
<showGrid>false</showGrid>
<diagramColor>-1</diagramColor>
<display>false</display>
<generatorId>08F7A71B-83CC-AA4A-D16C-1CC87A21FA78</generatorId>
<notation>1</notation>
<objectViews>
<OView class="oracle.dbtools.crest.swingui.relational.TVTable" oid="078E35D4-EBF8-C1A2-DFC6-2FD77A87A49D" otype="Table" vid="97910385-563C-BD4B-E68B-9D52530E80BE">
<hideElementsInCurrentOnly>false</hideElementsInCurrentOnly>
<bounds x="52" y="1172" width="170" height="110"/>
<generatorID>335C1099-43D5-9B17-DBDF-F9F79564BCB2</generatorID>
</OView>
<OView class="oracle.dbtools.crest.swingui.relational.TVTable" oid="17F9C456-85D7-A0A0-2E8B-8D9C872AAA91" otype="Table" vid="C5102B89-C859-765A-1077-A62C3CA8CA43">
<hideElementsInCurrentOnly>false</hideElementsInCurrentOnly>
<bounds x="1127" y="1223" width="170" height="110"/>
<generatorID>3633483B-1836-D3A3-7061-0E1D1F0EAB09</generatorID>
</OView>
<OView class="oracle.dbtools.crest.swingui.relational.TVTable" oid="1E33F98C-D225-E903-2DD2-9416455507EA" otype="Table" vid="01A47F8B-08CB-6AC9-07CA-97DE0D2C8186">
<hideElementsInCurrentOnly>false</hideElementsInCurrentOnly>
<bounds x="550" y="789" width="170" height="110"/>
<generatorID>55BDE54F-44E2-4253-32B4-68EA38FB9987</generatorID>
</OView>
<OView class="oracle.dbtools.crest.swingui.relational.TVTable" oid="209382C3-FC30-D5F6-C139-5AA03999183D" otype="Table" vid="E4AA0D3C-7184-1A37-9078-04AA28F79D8D">
<hideElementsInCurrentOnly>false</hideElementsInCurrentOnly>
<bounds x="841" y="1462" width="170" height="110"/>
<generatorID>E633AABA-CE72-4E9E-D99F-2262EB77867A</generatorID>
</OView>
<OView class="oracle.dbtools.crest.swingui.relational.TVTable" oid="31E4E7B6-9554-8BB6-DCF8-75EFD3FA024D" otype="Table" vid="399E2BE5-9322-DABE-ADDD-7254FBE76BB1">
<hideElementsInCurrentOnly>false</hideElementsInCurrentOnly>
<bounds x="769" y="837" width="170" height="110"/>
<generatorID>4FB00930-3B62-C59C-EDB6-8EA2B45C53FB</generatorID>
</OView>
<OView class="oracle.dbtools.crest.swingui.relational.TVTable" oid="51683132-DA2F-F499-DAAB-1C232F7EB9C9" otype="Table" vid="A50F80A8-5A26-C684-82A5-F1DFE42651A1">
<hideElementsInCurrentOnly>false</hideElementsInCurrentOnly>
<bounds x="1033" y="966" width="170" height="110"/>
<generatorID>DDA9C70A-646C-AF02-9266-86ADED2DD767</generatorID>
</OView>
<OView class="oracle.dbtools.crest.swingui.relational.TVTable" oid="5900ABEF-D0F0-7AB0-75FD-CB90DF4B6BC3" otype="Table" vid="D9C4D111-128F-0544-610A-9061709EF594">
<hideElementsInCurrentOnly>false</hideElementsInCurrentOnly>
<bounds x="697" y="1133" width="170" height="110"/>
<generatorID>A1DCBEC0-F99D-60F5-4AF3-9C0D6E4674C8</generatorID>
</OView>
<OView class="oracle.dbtools.crest.swingui.relational.TVTable" oid="591D46C5-FA11-990A-A17A-7184B37186BB" otype="Table" vid="7F6F6D0B-F295-57C8-3BBF-1C11FD98619B">
<hideElementsInCurrentOnly>false</hideElementsInCurrentOnly>
<bounds x="253" y="1437" width="170" height="110"/>
<generatorID>5DEAD86C-5716-E7CE-2537-32C946060A31</generatorID>
</OView>
<OView class="oracle.dbtools.crest.swingui.relational.TVTable" oid="7788950A-BD7B-4DED-5904-B48DBE78950C" otype="Table" vid="67C7251F-C14A-7DB5-34EC-44790A4DBFC6">
<hideElementsInCurrentOnly>false</hideElementsInCurrentOnly>
<bounds x="1214" y="967" width="170" height="110"/>
<generatorID>A2606BCA-3944-1165-B527-2E4ED7399374</generatorID>
</OView>
<OView class="oracle.dbtools.crest.swingui.relational.TVTable" oid="80326CEB-8103-0795-85B2-346D10BC965C" otype="Table" vid="C8CA5E61-24A1-9ADE-6958-604DC0786893">
<hideElementsInCurrentOnly>false</hideElementsInCurrentOnly>
<bounds x="605" y="1601" width="170" height="110"/>
<generatorID>8FB8CCEC-95D8-9660-0888-FBB66A76AEBF</generatorID>
</OView>
<OView class="oracle.dbtools.crest.swingui.relational.TVTable" oid="84D348EA-5016-1DDA-86E3-4F301C091FD4" otype="Table" vid="FF950D3A-1052-B83C-DB96-0076926FC655">
<hideElementsInCurrentOnly>false</hideElementsInCurrentOnly>
<bounds x="1126" y="1099" width="170" height="110"/>
<generatorID>C1007740-DFEA-B79D-991B-AFC30BF2A256</generatorID>
</OView>
<OView class="oracle.dbtools.crest.swingui.relational.TVTable" oid="95F88597-D948-623F-6881-F50F6AD90797" otype="Table" vid="0AC0670D-6E84-316A-B01B-83ED7EF75DBF">
<hideElementsInCurrentOnly>false</hideElementsInCurrentOnly>
<bounds x="450" y="919" width="170" height="110"/>
<generatorID>7D16061C-D92A-8745-1E6A-CF46FEE63C17</generatorID>
</OView>
<OView class="oracle.dbtools.crest.swingui.relational.TVTable" oid="96CA3CB1-1A09-C290-E312-8F732E4CD711" otype="Table" vid="701DB52E-F608-E11F-A47E-92B0A63E796F">
<hideElementsInCurrentOnly>false</hideElementsInCurrentOnly>
<bounds x="844" y="968" width="170" height="110"/>
<generatorID>0F732129-5378-A6B7-EBF8-5A0DD4CDEA61</generatorID>
</OView>
<OView class="oracle.dbtools.crest.swingui.relational.TVTable" oid="A0E309AF-AEBE-86C6-1034-A3B3CC09ADC5" otype="Table" vid="6D85C579-AC85-228F-3E9E-CBF0E73E2083">
<hideElementsInCurrentOnly>false</hideElementsInCurrentOnly>
<bounds x="943" y="1219" width="170" height="110"/>
<generatorID>DBF6256B-E375-A157-51D7-B6E0C083F68F</generatorID>
</OView>
<OView class="oracle.dbtools.crest.swingui.relational.TVTable" oid="A577F66D-419D-0029-17CC-3829DEED0FC0" otype="Table" vid="992EF979-9D72-FC17-C758-32F9F7982E95">
<hideElementsInCurrentOnly>false</hideElementsInCurrentOnly>
<bounds x="792" y="1592" width="170" height="110"/>
<generatorID>4DECDDD7-FF45-F0C6-9933-19579FA78693</generatorID>
</OView>
<OView class="oracle.dbtools.crest.swingui.relational.TVTable" oid="B11F7FE1-0267-5B1F-A6A9-B967D2528BD1" otype="Table" vid="0A1C91AB-CAF1-0AAA-06FE-6EFA7437888B">
<hideElementsInCurrentOnly>false</hideElementsInCurrentOnly>
<bounds x="944" y="1097" width="170" height="110"/>
<generatorID>7FB0AAF2-5AF4-A958-9A10-06D858B1A039</generatorID>
</OView>
<OView class="oracle.dbtools.crest.swingui.relational.TVTable" oid="CBA29A6B-3D89-0352-5EA6-749456204559" otype="Table" vid="8D79B08E-04B5-B800-62C9-8F5BB81DDD0D">
<hideElementsInCurrentOnly>false</hideElementsInCurrentOnly>
<bounds x="1129" y="1343" width="170" height="110"/>
<generatorID>40728018-5CCE-66C4-44A2-954F51FBB57F</generatorID>
</OView>
<OView class="oracle.dbtools.crest.swingui.relational.TVTable" oid="DB55AF40-58F4-067E-E037-2327F1BD1BBA" otype="Table" vid="5DD3C2D5-6035-920D-DE40-767D853DA16B">
<hideElementsInCurrentOnly>false</hideElementsInCurrentOnly>
<bounds x="253" y="1240" width="170" height="110"/>
<generatorID>42748A3D-09C1-402E-3277-A244040D4F3B</generatorID>
</OView>
<OView class="oracle.dbtools.crest.swingui.relational.TVTable" oid="DD612535-8D59-F7F2-2EB5-FC520B6F0FE3" otype="Table" vid="2DF647FB-43E6-473A-8A81-CAD9271153B6">
<hideElementsInCurrentOnly>false</hideElementsInCurrentOnly>
<bounds x="253" y="923" width="170" height="110"/>
<generatorID>7B8A2738-9D0C-10FB-DFC4-C8B0A6F186C2</generatorID>
</OView>
<OView class="oracle.dbtools.crest.swingui.relational.TVTable" oid="DE0B2DB5-9220-60D9-5E99-6DA29EC64300" otype="Table" vid="7DBCFDF6-7C16-F7E5-A79D-CC38E2F16845">
<hideElementsInCurrentOnly>false</hideElementsInCurrentOnly>
<bounds x="545" y="1462" width="170" height="110"/>
<generatorID>89DBAC46-741A-D650-FCB9-B1D92652B9A4</generatorID>
</OView>
<OView class="oracle.dbtools.crest.swingui.relational.TVTable" oid="FE51B2EF-0685-D9ED-79D7-71325C746876" otype="Table" vid="16F4055A-F65E-5235-CB92-A8E2B8BF2060">
<hideElementsInCurrentOnly>false</hideElementsInCurrentOnly>
<bounds x="253" y="1087" width="170" height="110"/>
<generatorID>C0F6A77F-47C8-1D4E-9DF6-D771B37CB9BE</generatorID>
</OView>
</objectViews>
<connectors>
<Connector class="oracle.dbtools.crest.swingui.relational.TVFKRelation" oid="04627E7E-6E7D-9C08-98D4-C6811EB734BC" otype="FKIndexAssociation" vid_source="701DB52E-F608-E11F-A47E-92B0A63E796F" vid_target="D9C4D111-128F-0544-610A-9061709EF594">
<hideElementsInCurrentOnly>false</hideElementsInCurrentOnly>
<backgroundColor>-16777216</backgroundColor>
<lineWidth>1</lineWidth>
<points>
<point x="844" y="1044"/>
<point x="867" y="1133"/>
</points>
</Connector>
<Connector class="oracle.dbtools.crest.swingui.relational.TVFKRelation" oid="0B6F4767-AE94-5513-62BD-3A34AA7881AC" otype="FKIndexAssociation" vid_source="A50F80A8-5A26-C684-82A5-F1DFE42651A1" vid_target="D9C4D111-128F-0544-610A-9061709EF594">
<hideElementsInCurrentOnly>false</hideElementsInCurrentOnly>
<backgroundColor>-16777216</backgroundColor>
<lineWidth>1</lineWidth>
<points>
<point x="1033" y="1073"/>
<point x="867" y="1133"/>
</points>
</Connector>
<Connector class="oracle.dbtools.crest.swingui.relational.TVFKRelation" oid="17753043-BA85-2A15-A153-E07D8C989747" otype="FKIndexAssociation" vid_source="01A47F8B-08CB-6AC9-07CA-97DE0D2C8186" vid_target="D9C4D111-128F-0544-610A-9061709EF594">
<hideElementsInCurrentOnly>false</hideElementsInCurrentOnly>
<backgroundColor>-16777216</backgroundColor>
<lineWidth>1</lineWidth>
<points>
<point x="697" y="899"/>
<point x="697" y="1133"/>
</points>
</Connector>
<Connector class="oracle.dbtools.crest.swingui.relational.TVFKRelation" oid="188C8A7E-0802-2FDC-D51C-9A2C89141ADE" otype="FKIndexAssociation" vid_source="7F6F6D0B-F295-57C8-3BBF-1C11FD98619B" vid_target="D9C4D111-128F-0544-610A-9061709EF594">
<hideElementsInCurrentOnly>false</hideElementsInCurrentOnly>
<backgroundColor>-16777216</backgroundColor>
<lineWidth>1</lineWidth>
<points>
<point x="398" y="1437"/>
<point x="724" y="1133"/>
</points>
</Connector>
<Connector class="oracle.dbtools.crest.swingui.relational.TVFKRelation" oid="33E65DB1-4171-CB29-B715-502664C0D239" otype="FKIndexAssociation" vid_source="16F4055A-F65E-5235-CB92-A8E2B8BF2060" vid_target="D9C4D111-128F-0544-610A-9061709EF594">
<hideElementsInCurrentOnly>false</hideElementsInCurrentOnly>
<backgroundColor>-16777216</backgroundColor>
<lineWidth>1</lineWidth>
<points>
<point x="423" y="1113"/>
<point x="697" y="1133"/>
</points>
</Connector>
<Connector class="oracle.dbtools.crest.swingui.relational.TVFKRelation" oid="3E5640A2-E9B8-D2BE-3A91-AA83139DD44D" otype="FKIndexAssociation" vid_source="C5102B89-C859-765A-1077-A62C3CA8CA43" vid_target="D9C4D111-128F-0544-610A-9061709EF594">
<hideElementsInCurrentOnly>false</hideElementsInCurrentOnly>
<backgroundColor>-16777216</backgroundColor>
<lineWidth>1</lineWidth>
<points>
<point x="1127" y="1241"/>
<point x="867" y="1140"/>
</points>
</Connector>
<Connector class="oracle.dbtools.crest.swingui.relational.TVFKRelation" oid="5D7B59B1-6ECE-7E45-6941-87A04BDA0560" otype="FKIndexAssociation" vid_source="97910385-563C-BD4B-E68B-9D52530E80BE" vid_target="D9C4D111-128F-0544-610A-9061709EF594">
<hideElementsInCurrentOnly>false</hideElementsInCurrentOnly>
<backgroundColor>-16777216</backgroundColor>
<lineWidth>1</lineWidth>
<points>
<point x="222" y="1208"/>
<point x="697" y="1133"/>
</points>
</Connector>
<Connector class="oracle.dbtools.crest.swingui.relational.TVFKRelation" oid="68ECF312-4BEC-98E5-7450-2FE10528B38A" otype="FKIndexAssociation" vid_source="E4AA0D3C-7184-1A37-9078-04AA28F79D8D" vid_target="D9C4D111-128F-0544-610A-9061709EF594">
<hideElementsInCurrentOnly>false</hideElementsInCurrentOnly>
<backgroundColor>-16777216</backgroundColor>
<lineWidth>1</lineWidth>
<points>
<point x="878" y="1462"/>
<point x="867" y="1140"/>
</points>
</Connector>
<Connector class="oracle.dbtools.crest.swingui.relational.TVFKRelation" oid="6CC8F4FB-3E86-085E-7546-FC0C542330B5" otype="FKIndexAssociation" vid_source="399E2BE5-9322-DABE-ADDD-7254FBE76BB1" vid_target="D9C4D111-128F-0544-610A-9061709EF594">
<hideElementsInCurrentOnly>false</hideElementsInCurrentOnly>
<backgroundColor>-16777216</backgroundColor>
<lineWidth>1</lineWidth>
<points>
<point x="842" y="947"/>
<point x="842" y="1133"/>
</points>
</Connector>
<Connector class="oracle.dbtools.crest.swingui.relational.TVFKRelation" oid="76B6E2CC-870D-002C-B985-101C577AAA87" otype="FKIndexAssociation" vid_source="C8CA5E61-24A1-9ADE-6958-604DC0786893" vid_target="D9C4D111-128F-0544-610A-9061709EF594">
<hideElementsInCurrentOnly>false</hideElementsInCurrentOnly>
<backgroundColor>-16777216</backgroundColor>
<lineWidth>1</lineWidth>
<points>
<point x="739" y="1601"/>
<point x="739" y="1133"/>
</points>
</Connector>
<Connector class="oracle.dbtools.crest.swingui.relational.TVFKRelation" oid="776DB3A2-D212-1033-8861-48CA5697C526" otype="FKIndexAssociation" vid_source="0AC0670D-6E84-316A-B01B-83ED7EF75DBF" vid_target="D9C4D111-128F-0544-610A-9061709EF594">
<hideElementsInCurrentOnly>false</hideElementsInCurrentOnly>
<backgroundColor>-16777216</backgroundColor>
<lineWidth>1</lineWidth>
<points>
<point x="620" y="1014"/>
<point x="697" y="1133"/>
</points>
</Connector>
<Connector class="oracle.dbtools.crest.swingui.relational.TVFKRelation" oid="84135468-2999-3024-4F9F-2FC820E4F361" otype="FKIndexAssociation" vid_source="0A1C91AB-CAF1-0AAA-06FE-6EFA7437888B" vid_target="D9C4D111-128F-0544-610A-9061709EF594">
<hideElementsInCurrentOnly>false</hideElementsInCurrentOnly>
<backgroundColor>-16777216</backgroundColor>
<lineWidth>1</lineWidth>
<points>
<point x="944" y="1133"/>
<point x="867" y="1133"/>
</points>
</Connector>
<Connector class="oracle.dbtools.crest.swingui.relational.TVFKRelation" oid="92C2E13D-2AA3-0847-D081-01EE46BFD5F2" otype="FKIndexAssociation" vid_source="67C7251F-C14A-7DB5-34EC-44790A4DBFC6" vid_target="D9C4D111-128F-0544-610A-9061709EF594">
<hideElementsInCurrentOnly>false</hideElementsInCurrentOnly>
<backgroundColor>-16777216</backgroundColor>
<lineWidth>1</lineWidth>
<points>
<point x="1214" y="1058"/>
<point x="867" y="1133"/>
</points>
</Connector>
<Connector class="oracle.dbtools.crest.swingui.relational.TVFKRelation" oid="943C8B37-341F-1282-2904-D61E286B4700" otype="FKIndexAssociation" vid_source="8D79B08E-04B5-B800-62C9-8F5BB81DDD0D" vid_target="D9C4D111-128F-0544-610A-9061709EF594">
<hideElementsInCurrentOnly>false</hideElementsInCurrentOnly>
<backgroundColor>-16777216</backgroundColor>
<lineWidth>1</lineWidth>
<points>
<point x="1136" y="1343"/>
<point x="835" y="1133"/>
</points>
</Connector>
<Connector class="oracle.dbtools.crest.swingui.relational.TVFKRelation" oid="9F2652CC-B833-B22F-55B1-977949B944D1" otype="FKIndexAssociation" vid_source="2DF647FB-43E6-473A-8A81-CAD9271153B6" vid_target="D9C4D111-128F-0544-610A-9061709EF594">
<hideElementsInCurrentOnly>false</hideElementsInCurrentOnly>
<backgroundColor>-16777216</backgroundColor>
<lineWidth>1</lineWidth>
<points>
<point x="423" y="999"/>
<point x="697" y="1133"/>
</points>
</Connector>
<Connector class="oracle.dbtools.crest.swingui.relational.TVFKRelation" oid="A37A207C-A5A4-4A85-6907-A0CEE9B435A1" otype="FKIndexAssociation" vid_source="7DBCFDF6-7C16-F7E5-A79D-CC38E2F16845" vid_target="D9C4D111-128F-0544-610A-9061709EF594">
<hideElementsInCurrentOnly>false</hideElementsInCurrentOnly>
<backgroundColor>-16777216</backgroundColor>
<lineWidth>1</lineWidth>
<points>
<point x="679" y="1462"/>
<point x="697" y="1140"/>
</points>
</Connector>
<Connector class="oracle.dbtools.crest.swingui.relational.TVFKRelation" oid="B456BE65-76A4-3797-8100-7EFF6F9E8F41" otype="FKIndexAssociation" vid_source="FF950D3A-1052-B83C-DB96-0076926FC655" vid_target="D9C4D111-128F-0544-610A-9061709EF594">
<hideElementsInCurrentOnly>false</hideElementsInCurrentOnly>
<backgroundColor>-16777216</backgroundColor>
<lineWidth>1</lineWidth>
<points>
<point x="1126" y="1119"/>
<point x="867" y="1133"/>
</points>
</Connector>
<Connector class="oracle.dbtools.crest.swingui.relational.TVFKRelation" oid="D6C1CA35-18AC-FF2F-378A-A49AC39D8046" otype="FKIndexAssociation" vid_source="5DD3C2D5-6035-920D-DE40-767D853DA16B" vid_target="D9C4D111-128F-0544-610A-9061709EF594">
<hideElementsInCurrentOnly>false</hideElementsInCurrentOnly>
<backgroundColor>-16777216</backgroundColor>
<lineWidth>1</lineWidth>
<points>
<point x="423" y="1255"/>
<point x="697" y="1140"/>
</points>
</Connector>
<Connector class="oracle.dbtools.crest.swingui.relational.TVFKRelation" oid="EFCB2017-1CE3-C270-6C91-59CAD3BEEF1F" otype="FKIndexAssociation" vid_source="6D85C579-AC85-228F-3E9E-CBF0E73E2083" vid_target="D9C4D111-128F-0544-610A-9061709EF594">
<hideElementsInCurrentOnly>false</hideElementsInCurrentOnly>
<backgroundColor>-16777216</backgroundColor>
<lineWidth>1</lineWidth>
<points>
<point x="953" y="1219"/>
<point x="847" y="1133"/>
</points>
</Connector>
</connectors>
</Diagram>
