<?xml version = '1.0' encoding = 'UTF-8'?>
<Relation class="oracle.dbtools.crest.model.design.logical.Relation" name="child apgar1" directorySegmentName="seg_0" id="036AA198-C252-8C6F-FEF0-43E9AAD7E13B">
<createdBy>User</createdBy>
<createdTime>2023-04-20 19:11:39 UTC</createdTime>
<ownerDesignName>prematures</ownerDesignName>
<engineerTo>
<item key="703C8260-0AB3-959A-EC1B-BAD160973F26" value="true"/>
</engineerTo>
<sourcePk>690BA573-6764-4598-6BAE-1AA174F0ABE1</sourcePk>
<identifying>false</identifying>
<optionalSource>true</optionalSource>
<optionalTarget>true</optionalTarget>
<sourceCardinality>1</sourceCardinality>
<sourceEntity>427391E2-01BC-E8DE-7004-E3B83971B054</sourceEntity>
<targetCardinalityString>*</targetCardinalityString>
<targetEntity>987CEFF6-68FE-C6E4-9ED0-7ADB62C5D470</targetEntity>
<transferable>true</transferable>
</Relation>
