<?xml version = '1.0' encoding = 'UTF-8'?>
<TableProxyOraclev12c class="oracle.dbtools.crest.model.design.storage.oracle.v12c.TableProxyOraclev12c" name="breathing_failure" directorySegmentName="seg_0" id="ADB27155-2E1E-8D6F-0D09-15D3B0E868AA">
<createdBy>User</createdBy>
<createdTime>2023-03-14 19:53:01 UTC</createdTime>
<ownerDesignName>prematures</ownerDesignName>
<logging>YES</logging>
<partitionedRowMovement>DISABLE</partitionedRowMovement>
<temporaryChanged>false</temporaryChanged>
<accessDriverType>oracle_loader</accessDriverType>
<rejectLimit></rejectLimit>
<columnProxies itemClass="oracle.dbtools.crest.model.design.storage.oracle.v12c.ColumnProxyOraclev12c">
<ColumnProxy name="breathing_failure_name" id="0AD10BF9-8458-4828-6647-F1058F008D18">
<createdBy>User</createdBy>
<createdTime>2023-03-14 19:53:01 UTC</createdTime>
<ownerDesignName>prematures</ownerDesignName>
</ColumnProxy>
<ColumnProxy name="breathing_failure_id" id="B77254D6-EFF1-3B63-20E4-175510EEBA37">
<createdBy>User</createdBy>
<createdTime>2023-03-14 19:53:01 UTC</createdTime>
<ownerDesignName>prematures</ownerDesignName>
</ColumnProxy>
</columnProxies>
<primaryKeys>
<PrimaryKey class="oracle.dbtools.crest.model.design.storage.oracle.v10g.PKProxyOraclev10g" name="breathing_failure_pk" id="3A6BC547-8D6B-3E30-2E07-945B6F13BD37">
<createdBy>User</createdBy>
<createdTime>2023-03-14 19:53:01 UTC</createdTime>
<ownerDesignName>prematures</ownerDesignName>
<indexSort>SORTED</indexSort>
</PrimaryKey>
</primaryKeys>
<uniqueKeys>
<UniqueKey class="oracle.dbtools.crest.model.design.storage.oracle.v10g.UniqueOraclev10g" name="breathing_failure_breathing_failure_name_un" id="8A13FF72-FA6D-F96C-3688-8BA5FAED2154">
<createdBy>User</createdBy>
<createdTime>2023-03-14 19:53:01 UTC</createdTime>
<ownerDesignName>prematures</ownerDesignName>
<indexSort>SORTED</indexSort>
</UniqueKey>
</uniqueKeys>
</TableProxyOraclev12c>
